pmpackage/__init__.py
pmpackage/functions.py
Postal_Methods_2.0_API-2.0.dist-info/METADATA
Postal_Methods_2.0_API-2.0.dist-info/WHEEL
Postal_Methods_2.0_API-2.0.dist-info/top_level.txt
Postal_Methods_2.0_API-2.0.dist-info/RECORD
