Metadata-Version: 2.1
Name: Postal-Methods-2.0-API
Version: 2.0
Summary: Postal Methods API SDK for Python
Home-page: UNKNOWN
Author: Postal Methods
Author-email: 
License: UNKNOWN
Platform: UNKNOWN
Classifier: Programming Language :: Python :: 3
Classifier: License :: OSI Approved :: MIT License
Classifier: Operating System :: OS Independent
Requires-Python: >=3.6
